examples/__init__.py
examples/autodiff_evaluation_xlumina.py
examples/numerical_methods_evaluation_diffractio.py
examples/scalar_diffractio.py
examples/scalar_xlumina.py
examples/vectorial_diffractio.py
examples/vectorial_xlumina.py
experiments/__init__.py
experiments/four_f_optical_table.py
experiments/four_f_optimizer.py
experiments/generate_synthetic_data.py
experiments/hybrid_optimizer.py
experiments/hybrid_sharp_optical_table.py
experiments/hybrid_sted_optical_table.py
experiments/hybrid_with_fixed_PM.py
experiments/six_times_six_ansatz_with_fixed_PM.py
tests/__init__.py
tests/test_optical_elements.py
tests/test_toolbox.py
tests/test_vectorized_optics.py
tests/test_wave_optics.py
xlumina/__init__.py
xlumina/loss_functions.py
xlumina/optical_elements.py
xlumina/toolbox.py
xlumina/vectorized_optics.py
xlumina/wave_optics.py
xlumina-1.0.0.dist-info/LICENSE
xlumina-1.0.0.dist-info/METADATA
xlumina-1.0.0.dist-info/WHEEL
xlumina-1.0.0.dist-info/top_level.txt
xlumina-1.0.0.dist-info/RECORD
