Metadata-Version: 2.1
Name: xlumina
Version: 1.0.0
Summary: XLuminA: An Auto-differentiating Discovery Framework for Super-Resolution Microscopy
Home-page: https://github.com/artificial-scientist-lab/XLuminA
Author: artificial-scientist-lab
Author-email: carla.rodriguez@mpl.mpg.de, soeren.arlt@mpl.mpg.de, mario.krenn@mpl.mpg.de,
License: MIT
Platform: ALL
Classifier: Operating System :: OS Independent
Classifier: Programming Language :: Python :: 3.10
Classifier: Programming Language :: Python :: 3.11
Requires-Python: >=3.10
License-File: LICENSE
Requires-Dist: jax==0.4.33
Requires-Dist: numpy
Requires-Dist: optax==0.2.3
Requires-Dist: scipy==1.14.1
Requires-Dist: matplotlib
